rads/__init__.py
rads/__main__.py
rads/log_interface.py
rads/command/__init__.py
rads/command/schedule_pass.py
rads/database/__init__.py
rads/database/insert.py
rads/database/models.py
rads/database/query.py
rads/database/request_data.py
rads/database/update.py
rads/ui/__init__.py
rads/ui/approve_deny_window.py
rads/ui/archive_window.py
rads/ui/eb_request_window.py
rads/ui/main_menu.py
rads/ui/schedule_window.py
rads/ui/tables/__init__.py
rads/ui/tables/eb_pass_table.py
rads/ui/tables/request_table.py
uniclogs_rads-0.1.1.dist-info/LICENSE
uniclogs_rads-0.1.1.dist-info/METADATA
uniclogs_rads-0.1.1.dist-info/WHEEL
uniclogs_rads-0.1.1.dist-info/entry_points.txt
uniclogs_rads-0.1.1.dist-info/top_level.txt
uniclogs_rads-0.1.1.dist-info/RECORD
