Metadata-Version: 2.1
Name: uniclogs-rads
Version: 0.1.1
Summary: Request Approve Deny Service
Home-page: https://github.com/oresat/uniclogs-software
Author: Ryan Medick
Author-email: rmedick@pdx.edu
Maintainer: Ryan Medick
Maintainer-email: rmedick@pdx.edu
License: GPLv3
Platform: UNKNOWN
Classifier: Programming Language :: Python
Requires-Python: >=3.5
Requires-Dist: loguru (>=0.5.0)
Requires-Dist: sqlalchemy (>=1.3.18)
Requires-Dist: reverse-geocoder (>=1.5.1)
Requires-Dist: pass-calculator (>=1.0.1)
